setup.cfg
setup.py
docs/CHANGES.txt
docs/INSTALL.txt
docs/LICENSE.txt
p4a/__init__.py
p4a.z2utils.egg-info/PKG-INFO
p4a.z2utils.egg-info/SOURCES.txt
p4a.z2utils.egg-info/dependency_links.txt
p4a.z2utils.egg-info/entry_points.txt
p4a.z2utils.egg-info/namespace_packages.txt
p4a.z2utils.egg-info/not-zip-safe
p4a.z2utils.egg-info/requires.txt
p4a.z2utils.egg-info/top_level.txt
p4a/z2utils/__init__.py
p4a/z2utils/configure.zcml
p4a/z2utils/indexing.py
p4a/z2utils/patches.py
p4a/z2utils/pkgloader.py
p4a/z2utils/pkgloader.txt
p4a/z2utils/utils.py
p4a/z2utils/tests/__init__.py
p4a/z2utils/tests/test_all.py
p4a/z2utils/tests/samples/dir1/ns/__init__.py
p4a/z2utils/tests/samples/dir1/ns/pkg1/__init__.py
p4a/z2utils/tests/samples/dir2/ns/__init__.py
p4a/z2utils/tests/samples/dir2/ns/pkg2/__init__.py