Metadata-Version: 1.0
Name: p4a.z2utils
Version: 1.0.2
Summary: Miscellaneous utilities for Zope 2
Home-page: UNKNOWN
Author: Rocky Burt
Author-email: rocky@serverzen.com
License: GPL
Platform: UNKNOWN
Classifier: Framework :: Zope2
Classifier: Framework :: Zope3
Classifier: Programming Language :: Python
Classifier: Topic :: Software Development :: Libraries :: Python Modules
